{
  "How_it_works": "Как это работает?",
  "Application_area": "Область применения",
  "Our_team": "Наша команда",
  "Main_description":"Мы разработали передовое устройство, способное переосмыслить ваш опыт взаимодействия с технологичными объектами.",
  "order": "Заказать",
  "How_it_works_descr": "Невероятный контроль,сверхточные браслеты отслеживают любой импульс вашего тела.  Устройство точного управления преобразует движения ваших пальцев с помощью кожно-гальванических и объемных датчиков в электрические сигналы управления.",
  "UAV_Control": "Управление БПЛА",
  "Application_area_descr": "Преобразует движения ваших пальцев с помощью гальванических и объемных датчиков в электрические сигналы управления. Невероятный контроль, сверхточные браслеты отслеживают любой импульс вашего тела. Мы разработали передовое устройство, способное переосмыслить ваш опыт взаимодействия с технологичными объектами.",
  "Use_as_mouse": "Использование в качестве мыши",
  "UGV_control": "Управление назмеными РТС",
  "Kozulyaev": "Алексей Козуляев",
  "Kozulyaev_descr": "Продвижение, маркетинг, финансирование",
  "Konotopova": "Елена Конотопова",
  "Konotopova_descr": "Патентные и организационные вопросы",
  "Saveliev": "Антон Савельев",
  "Saveliev_descr": "Разработка и производство",
  "Andreeva": "Полина Андреева",
  "Andreeva_descr": "Продажи и координация работы над проектами",
  "Borshevsky": "Иван Борщевский",
  "Borshevsky_descr": "Когнитивные исследования и жестовые сигналы",
  "form_header": "Хотите заказать устройство MyoMouse?",
  "leave_request": "Просто оставьте заявку!",
  "enter_name": "Введите имя",
  "phone_number": "Номер телефона",
  "submit": "Оставить заявку"

}